spektro/__init__.py
spektro/loader.py
spektro/spektro.py
tests/__init__.py
tests/test_loader.py
spektro-0.0.3.dist-info/LICENSE
spektro-0.0.3.dist-info/METADATA
spektro-0.0.3.dist-info/WHEEL
spektro-0.0.3.dist-info/top_level.txt
spektro-0.0.3.dist-info/RECORD
